highwire-0.7.0.dist-info/METADATA
highwire-0.7.0.dist-info/WHEEL
highwire-0.7.0.dist-info/entry_points.txt
highwire/__init__.py
highwire/async_streams.py
highwire/events.py
highwire/exceptions.py
highwire/folds.py
highwire/samplers.py
highwire/selections.py
highwire/signals.py
highwire/streams.py
highwire/variables.py
highwire-0.7.0.dist-info/RECORD
